data/__init__.py
data/cpp_template.txt
data/cpp_template_info.txt
data/data.py
data/get_template.py
data/py_template.txt
data/py_template_info.txt
run/__init__.py
run/cp_run.py
run/main.py
run/run.py
settings/.trained
settings/__init__.py
settings/_first_load_.py
settings/bot.json
settings/compiler.py
settings/config.py
settings/default.conf
settings/logs.py
settings/settings.conf
settings/settings.py
system/__about__.py
system/__init__.py
system/features_installation.py
system/get_time.py
system/install.py
system/internet.py
system/notifications.py
system/path.py
system/screen_text.py
tools/ConfigParser.py
tools/TODO_management.py
tools/__init__.py
tools/assistant.py
tools/calculation.py
tools/credits.py
tools/downloader.py
tools/google_answer.py
tools/json_manager.py
tools/run_program.py
tools/shell.py
tools/string_processing.py
tools/wiki_search.py
tools/AI/.learnt
tools/AI/__init__.py
tools/AI/ai.py
tools/AI/conversations.json
tools/AI/data.py
tools/OJ/__init__.py
tools/OJ/client.py
tools/OJ/cp.py
tools/OJ/socket_manager.py
tools/OJ/test.py
tools/OJ/testing.py
tools/browser/__init__.py
tools/browser/goto.py
tools/browser/search.py
tools/interaction/__init__.py
tools/interaction/get_audio.py
tools/interaction/speak.py
ai_virtual_assistant-1.0.4.dist-info/LICENSE.txt
ai_virtual_assistant-1.0.4.dist-info/METADATA
ai_virtual_assistant-1.0.4.dist-info/WHEEL
ai_virtual_assistant-1.0.4.dist-info/entry_points.txt
ai_virtual_assistant-1.0.4.dist-info/top_level.txt
ai_virtual_assistant-1.0.4.dist-info/RECORD
