Metadata-Version: 2.1
Name: ai-virtual-assistant
Version: 1.0.4
Summary: CLI virtual assitant for competitive programming
Home-page: https://github.com/Saurav-Paul/AI-virtual-assistant-python
Author: Saurav Paul
Author-email: sauravpaul.sunny@gmail.com
License: MIT License
Keywords: ai virtual assitant
Platform: UNKNOWN
Classifier: Development Status :: 5 - Production/Stable
Classifier: Environment :: Console
Classifier: Intended Audience :: End Users/Desktop
Classifier: Operating System :: POSIX :: Linux
Classifier: Operating System :: MacOS :: MacOS X
Classifier: License :: OSI Approved :: MIT License
Requires-Python: >=3.5
Requires-Dist: beautifulsoup4
Requires-Dist: fuzzywuzzy
Requires-Dist: google
Requires-Dist: lxml
Requires-Dist: online-judge-api-client
Requires-Dist: online-judge-tools
Requires-Dist: plyer
Requires-Dist: pyfiglet
Requires-Dist: requests
Requires-Dist: tcgen
Requires-Dist: termcolor
Requires-Dist: tqdm
Requires-Dist: wget
Requires-Dist: wikipedia-api
Requires-Dist: wolframalpha
Requires-Dist: selenium
